setup.py
nxosNCRPC/__init__.py
nxosNCRPC.egg-info/PKG-INFO
nxosNCRPC.egg-info/SOURCES.txt
nxosNCRPC.egg-info/dependency_links.txt
nxosNCRPC.egg-info/top_level.txt