Metadata-Version: 1.1
Name: nxosNCRPC
Version: 0.1
Summary: Python library to generate Cisco Nexus NETCONF RPC messages, hello and close messages
Home-page: https://github.com/DavidJohnGee/nxosNCRPC
Author: David Gee
Author-email: david.gee@ipengineer.net
License: Apache License 2.0
Keywords: NETCONF,NETCONF Python client,Juniper Optimization,Cisco NXOS Optimization
Platform: Posix; OS X; Windows
Classifier: Development Status :: 5 - Production/Stable
Classifier: Programming Language :: Python :: 2.6
Classifier: Programming Language :: Python :: 2.7
Classifier: Topic :: System :: Networking
Classifier: Intended Audience :: Developers
Classifier: Operating System :: OS Independent
Classifier: Topic :: Software Development :: Libraries :: Python Modules
